pytorch_toolz/__init__.py
pytorch_toolz/__version__.py
pytorch_toolz/functools.py
pytorch_toolz/itertools.py
pytorch_toolz/operator.py
pytorch_toolz-1.2.2.dist-info/METADATA
pytorch_toolz-1.2.2.dist-info/WHEEL
pytorch_toolz-1.2.2.dist-info/licenses/LICENSE
pytorch_toolz-1.2.2.dist-info/RECORD
