Metadata-Version: 2.1
Name: pytorch_toolz
Version: 1.2.2
Summary: Functional addition to pytorch for better model-building
Project-URL: Homepage, https://github.com/Ilykuleshov/pytorch-toolz
Project-URL: Bug Tracker, https://github.com/Ilykuleshov/pytorch-toolz/issues
Author-email: Ilya <ilykuleshov@yandex.ru>
License-Expression: MIT
License-File: LICENSE
Classifier: License :: OSI Approved :: MIT License
Classifier: Operating System :: OS Independent
Classifier: Programming Language :: Python :: 3
Requires-Python: >=3.7
